{"corona": {"name": {"attribute_structure": {"type": "text"}}, "summary": {"attribute_structure": {"type": "text"}}, "description": {"attribute_structure": {"type": "text"}}, "approvalStatus": {"type": "dropdown", "source": ["approved", "unapproved", "check"]}, "supercategories": {"attribute_structure": {"type": "text"}}, "ean": {"type": "numeric"}, "externalSalesUnit": {"type": "numeric"}, "unit": {"type": "dropdown", "source": ["CJ", "M2", "KG", "UN"]}, "conversionValue": {"type": "numeric"}, "conversionUnit": {"type": "dropdown", "source": ["FT2", "G", "GAL", "IN2", "KG", "L", "LB", "M2", "ML", "OZ"]}, "weight": {"type": "numeric"}, "relevance": {"type": "dropdown", "source": ["HIGH_RELEVANCE", "LOW_RELEVANCE", "MEDIUM_RELEVANCE", "NO_RELEVANCE", "VERY_HIGH_RELEVANCE", "VERY_LOW_RELEVANCE"]}, "productRequest": {"type": "checkbox"}, "colorSelector": {"type": "checkbox"}, "hasPriorityVariant": {"type": "checkbox"}, "areaCovered": {"type": "numeric"}, "areaUnit": {"type": "dropdown", "source": ["M2", "CM2"]}, "showCalculator": {"type": "checkbox"}, "wastePerecentage": {"type": "numeric"}, "flag": {"type": "dropdown", "source": ["PRONTO", "FREE_SHIPPING", "SPECIAL_PRICE", "EXCLUSIVE", "ANNIVERSARY", "POTENTIAL_PROMOTION", "NEW"]}, "recommendationsForUse": {"attribute_structure": {"type": "text"}}, "recommendationsForInstalation": {"attribute_structure": {"type": "text"}}, "recommendationsForApplying": {"attribute_structure": {"type": "text"}}, "recommendationsForCleaning": {"attribute_structure": {"type": "text"}}, "advantages": {"attribute_structure": {"type": "text"}}, "specialAttributes": {"attribute_structure": {"type": "text"}}, "extendedContent": {"attribute_structure": {"type": "text"}}, "presentation": {"type": "dropdown", "source": ["BOX", "SET", "UNIT"]}, "technicalDocuments": {"attribute_structure": {"type": "text"}}, "blueprints": {"attribute_structure": {"type": "text"}}, "seoTitle": {"attribute_structure": {"type": "text"}}, "seoDescription": {"attribute_structure": {"type": "text"}}, "seoRobots": {"type": "dropdown", "source": ["INDEX_FOLLOW", "INDEX_NOFOLLOW", "NOINDEX", "NOINDEX_FOLLOW", "NOINDEX_NOFOLLOW"]}, "ogTitle": {"attribute_structure": {"type": "text"}}, "ogDescription": {"attribute_structure": {"type": "text"}}}, "especificaciones-accesorios": {"profundidad": {"type": "numeric"}, "temperatura-de-uso": {"attribute_structure": {"type": "text"}}}, "especificaciones-combos-y-kits": {"componentes": {"type": "dropdown", "source": ["accesorios", "barra", "cepillera", "dispensador-de-jabon", "griferia", "jabonera", "lavamanos-con-pedestal", "lavamanos-sin-pedestal", "mueble-con-lavamanos-a-piso", "mueble-con-lavamanos-elevado", "percha", "portarrollo", "sanitario-de-dos-piezas", "sanitario-de-una-pieza", "toallero"]}, "numero-de-piezas": {"type": "numeric"}, "tipo-de-sifon": {"type": "dropdown", "source": ["expuesto", "oculto"]}}, "especificaciones-comunes-a": {"areas-de-uso": {"type": "dropdown", "source": ["alcobas", "areas-comerciales", "areas-exteriores", "areas-exteriores-techadas", "bano", "biblioteca", "cocina", "escaleras", "hall", "pasillo", "piscina", "sala-comedor", "terrazas"]}, "diseno": {"attribute_structure": {"type": "text"}}}, "especificaciones-comunes-b": {"contenido-del-producto": {"attribute_structure": {"type": "text"}}, "precauciones": {"attribute_structure": {"type": "text"}}, "presentacion": {"type": "dropdown", "source": ["balde", "bolsa", "botella", "bulto", "caja", "cunete", "galon", "garrafa", "tambor", "tubo", "unidad"]}, "rendimiento": {"attribute_structure": {"type": "text"}}, "tiempo-de-secado": {"attribute_structure": {"type": "text"}}}, "especificaciones-comunes-c": {"consumo-de-agua": {"type": "numeric"}, "forma": {"type": "dropdown", "source": ["alongado", "cuadrado", "ovalado", "rectangular", "redondo"]}, "tipo-de-instalacion": {"type": "dropdown", "source": ["a-pared", "a-piso", "elevado", "facil-click", "sobre-meson"]}, "tipo-de-manija-o-accionamiento": {"type": "dropdown", "source": ["cruceta", "oculta", "palanca", "pomo", "push", "push-mesa", "push-pared", "sensor", "tiradera", "triceta"]}}, "especificaciones-duchas": {"dimension-de-la-regadera": {"attribute_structure": {"type": "text"}}, "longitud-del-brazo": {"type": "numeric"}, "tipo-de-regadera": {"type": "dropdown", "source": ["cobertura-envolvente", "cobertura-estandar", "cobertura-focalizada", "regadera-con-brazo", "regadera-con-funciones", "regadera-diametro-amplio", "regadera-sencilla", "regadera-sin-brazo", "valores-a-adicionar"]}, "tipo-mezclador": {"type": "dropdown", "source": ["monocontrol", "monocontrol-con-desviador", "ocho-pulgadas", "sencillo"]}}, "especificaciones-gaso-electro": {"color": {"attribute_structure": {"type": "text"}}, "eficiencia-energetica": {"attribute_structure": {"type": "text"}}, "especificaciones-gaso-electro": {"attribute_structure": {"type": "text"}}, "marca": {"type": "dropdown", "source": ["abba", "airon", "ariston", "challenger", "electric", "mabe-general", "teka"]}, "observaciones": {"attribute_structure": {"type": "text"}}, "tipo-de-sistema": {"type": "dropdown", "source": ["128piezas", "40piezas", "48piezas", "60piezas", "70piezas", "75piezas", "dropdown", "electrico", "gas-natural", "gas-propano", "isla", "mixto-electro-gas", "mueble", "pared-peninsula", "ultraslim"]}, "tipo-instalacion": {"type": "dropdown", "source": ["empotrar", "piso"]}, "voltaje": {"attribute_structure": {"type": "text"}}}, "especificaciones-generales": {"acabado": {"type": "dropdown", "source": ["brillante", "cromado", "mate", "satinado", "semibrillante", "semimate"]}, "alto": {"type": "numeric"}, "ancho": {"type": "numeric"}, "calidad": {"attribute_structure": {"type": "text"}}, "coleccion": {"attribute_structure": {"type": "text"}}, "espesor-mm": {"attribute_structure": {"type": "text"}}, "fabricado-por": {"attribute_structure": {"type": "text"}}, "fabricante": {"attribute_structure": {"type": "text"}}, "garantia": {"attribute_structure": {"type": "text"}}, "garantias-de-otros-componentes": {"attribute_structure": {"type": "text"}}, "incluye": {"attribute_structure": {"type": "text"}}, "largo": {"type": "numeric"}, "linea": {"attribute_structure": {"type": "text"}}, "marca": {"attribute_structure": {"type": "text"}}, "materiales": {"attribute_structure": {"type": "text"}}, "no-incluye": {"attribute_structure": {"type": "text"}}, "paisdeorigen": {"attribute_structure": {"type": "text"}}, "premios": {"attribute_structure": {"type": "text"}}, "productos-compatibles": {"attribute_structure": {"type": "text"}}, "resistencia": {"attribute_structure": {"type": "text"}}, "tecnologias": {"attribute_structure": {"type": "text"}}, "uso": {"type": "dropdown", "source": ["hogar", "institucional", "residencial"]}}, "especificaciones-griferias": {"altura-de-la-griferia": {"type": "dropdown", "source": ["altura-de-la-griferia-alta", "altura-de-la-griferia-baja", "altura-de-la-griferia-media"]}, "capacidad-de-flujo": {"attribute_structure": {"type": "text"}}, "observaciones": {"attribute_structure": {"type": "text"}}, "rango-de-presion-de-agua": {"attribute_structure": {"type": "text"}}, "sistema-antivandalico": {"attribute_structure": {"type": "text"}}, "sistema-de-accionamiento": {"attribute_structure": {"type": "text"}}, "temperatura-de-uso": {"attribute_structure": {"type": "text"}}, "tipo-de-chorro": {"type": "dropdown", "source": ["cascada", "espumoso", "hidromasaje", "tipo-lluvia"]}, "tipo-de-griferia": {"type": "dropdown", "source": ["cuatro-pulgadas", "de-pared", "monocontrol", "ocho-pulgadas", "sencilla"]}}, "especificaciones-herramientas": {"caracteristicas-funcionales": {"attribute_structure": {"type": "text"}}}, "especificaciones-materiales-limpiadores-pegantes": {"adherencia": {"attribute_structure": {"type": "text"}}, "dilucion": {"attribute_structure": {"type": "text"}}, "duracion-de-la-mezcla": {"attribute_structure": {"type": "text"}}, "tiempo-abierto": {"attribute_structure": {"type": "text"}}, "tiempo-para-emboquillar": {"attribute_structure": {"type": "text"}}}, "especificaciones-muebles": {"profundidad": {"type": "numeric"}, "resistente-humedad": {"attribute_structure": {"type": "text"}}, "tiempo-de-armado-estimado": {"type": "numeric"}, "tipo-de-canto": {"type": "dropdown", "source": ["flexible", "rigido"]}, "tipo-de-cierre": {"type": "dropdown", "source": ["lento", "push-to-open-suave", "seco", "suave"]}, "tipo-de-herrajes": {"attribute_structure": {"type": "text"}}}, "especificaciones-muebles-bano": {"material-del-lavamanos": {"type": "dropdown", "source": ["ceramica", "porcelana", "vidrio"]}, "material-del-meson": {"type": "dropdown", "source": ["corona-stone", "porcelana"]}}, "especificaciones-muebles-cocina": {"caracteristicas-de-la-cubierta": {"attribute_structure": {"type": "text"}}, "material-del-lavaplatos": {"attribute_structure": {"type": "text"}}}, "especificaciones-muebles-lavadero": {"material-del-lavadero": {"attribute_structure": {"type": "text"}}}, "especificaciones-pinturas": {"cuarteamiento-alto-espesor": {"attribute_structure": {"type": "text"}}, "cuarteamiento-superficial": {"attribute_structure": {"type": "text"}}, "fabricado-por": {"attribute_structure": {"type": "text"}}, "lavabilidad": {"type": "dropdown", "source": ["lavabilidad-alta", "lavabilidad-baja", "lavabilidad-media"]}, "lote-fecha-fabricacion": {"attribute_structure": {"type": "text"}}, "poder-cubriente": {"attribute_structure": {"type": "text"}}, "remocion-manchas-lavabilidad": {"attribute_structure": {"type": "text"}}, "resistencia-abrasion": {"attribute_structure": {"type": "text"}}, "resistencia-agua": {"attribute_structure": {"type": "text"}}, "resistencia-hongos-algas": {"attribute_structure": {"type": "text"}}, "retencion-olor": {"attribute_structure": {"type": "text"}}, "toxicidad": {"attribute_structure": {"type": "text"}}}, "especificaciones-plomeria": {"alto-plomeria": {"type": "numeric"}, "ancho-plomeria": {"type": "numeric"}, "especificaciones": {"attribute_structure": {"type": "text"}}, "largo-plomeria": {"type": "numeric"}}, "especificaciones-pozos": {"diametro-del-desague": {"type": "numeric"}, "dimensiones-del-pozo": {"attribute_structure": {"type": "text"}}, "profundidad-del-pozo": {"type": "numeric"}, "sistema-antivandalico": {"attribute_structure": {"type": "text"}}, "tipo-de-desague": {"type": "dropdown", "source": ["expuesto", "oculto"]}, "tipo-de-lavamanos": {"attribute_structure": {"type": "text"}}}, "especificaciones-revestimientos": {"aspecto": {"type": "dropdown", "source": ["caras-diferenciadas", "caras-unicas", "multitono"]}, "formato": {"attribute_structure": {"type": "text"}}, "lote-fecha-fabricacion": {"attribute_structure": {"type": "text"}}, "m2-por-caja": {"type": "numeric"}, "pais-origen": {"attribute_structure": {"type": "text"}}, "piezas-por-caja": {"type": "numeric"}, "resistencia-a-las-manchas": {"type": "dropdown", "source": ["clase-1", "clase-2", "clase-3", "clase-4", "clase-5"]}, "superficie": {"attribute_structure": {"type": "text"}}, "tamaño": {"attribute_structure": {"type": "text"}}, "trafico": {"type": "dropdown", "source": ["comercial-general", "comercial-moderado", "residencial-general", "residencial-moderado", "solo-pared", "todo-trafico"]}, "unidad-de-embalaje": {"attribute_structure": {"type": "text"}}}, "especificaciones-sanitarios": {"accesibilidad": {"attribute_structure": {"type": "text"}}, "altura-de-la-taza": {"type": "numeric"}, "capacidad-de-descarga": {"type": "numeric"}, "espejo-de-agua": {"attribute_structure": {"type": "text"}}, "perfil-de-la-taza": {"type": "dropdown", "source": ["alongado", "redondo"]}, "sistema-antivandalico": {"attribute_structure": {"type": "text"}}, "sistema-de-descarga": {"type": "dropdown", "source": ["boton-dual-azul-corona", "boton-tipo-push", "palanca"]}, "tipo-de-asiento": {"type": "dropdown", "source": ["cierre-lento", "cierre-tradicional"]}, "tipo-de-sifon": {"type": "dropdown", "source": ["expuesto", "oculto"]}, "tipo-de-tanque": {"attribute_structure": {"type": "text"}}, "tipo-de-valvula": {"attribute_structure": {"type": "text"}}}}